projects/apb/master/apb_master.v
// -----------------------------------------------------------------------------
// Module: APB_master
// Description: A formally verified APB master module
// 
// Author:       fjpolo
// Date:         27.01.2025
// Email:        fjpolo@gmail.com
// Github:       @fjpolo
// 
// License: 
// This code is released under the following terms:
// - You are free to use, modify, and distribute this code for any purpose.
// - You must retain this header in all copies or substantial portions of the code.
// 
// Disclaimer:
// This code is provided "as is," without warranty of any kind, express or implied,
// including but not limited to the warranties of merchantability, fitness for a
// particular purpose, and non-infringement. In no event shall the author be liable
// for any claim, damages, or other liability, whether in an action of contract, tort,
// or otherwise, arising from, out of, or in connection with the code or the use
// or other dealings in the code.
// -----------------------------------------------------------------------------
`default_nettype none

module apb_master(
    input   wire    [0:0]   i_clk,      // APB clock
    input   wire    [0:0]   i_reset_n,  // APB reset (active low)
    input   wire    [31:0]  i_addr,     // Address for the transaction
    input   wire    [0:0]   i_start,    // Start signal to initiate a transaction
    input   wire    [0:0]   i_write,    // Write/read control (1 = write, 0 = read)
    input   wire    [31:0]  i_wdata,    // Write data (for write transactions)
    output  reg     [0:0]   o_done,     // Transaction completion signal
    output  reg     [31:0]  o_rdata,    // Read data (for read transactions)
    output  reg     [0:0]   o_slverr,   // Slave error
    output  reg     [31:0]  PADDR,      // APB address
    output  reg     [0:0]   PWRITE,     // APB write/read control (1 = write, 0 = read)
    output  reg     [31:0]  PWDATA,     // APB write data
    output  reg     [0:0]   PSELx,      // APB slave select
    output  reg     [0:0]   PENABLE,    // APB enable
    input   wire    [31:0]  PRDATA,     // APB read data
    input   wire    [0:0]   PREADY,     // APB ready signal from slave
    input   wire    [0:0]   PSLVERR     // APB slave error signal
  );
  

    // State encoding
    localparam IDLE = 0;
    localparam SETUP = 1;
    localparam ACCESS = 2;
    
    reg [1:0] state;
  
    // Initialize state and outputs
    initial begin
      state = IDLE;
      PADDR = 32'h0;
      PWRITE = 1'b0;
      PWDATA = 32'h0;
      PSELx = 1'b0;
      PENABLE = 1'b0;
      o_done = 1'b0;
      o_rdata = 32'h0;
      o_slverr = 1'b0;
    end
  
    // APB master FSM
    always @(posedge i_clk) begin
      if (!i_reset_n) begin
        // Reset state
        state <= IDLE;
        PADDR <= 32'h0;
        PWRITE <= 1'b0;
        PWDATA <= 32'h0;
        PSELx <= 1'b0;
        PENABLE <= 1'b0;
        o_done <= 1'b0;
        o_rdata <= 32'h0;
        o_slverr <= 1'b0;
      end else begin
        case (state)
          IDLE: begin
            // Wait for start signal
            if (i_start) begin
              PADDR <= i_addr;
              PWRITE <= i_write;
              PWDATA <= i_wdata;
              PSELx <= 1'b1;
              PENABLE <= 1'b0;
              state <= SETUP;
            end
          end
  
          SETUP: begin
            // Assert PENABLE in the next cycle
            PENABLE <= 1'b1;
            state <= ACCESS;
          end
  
          ACCESS: begin
            if (PREADY) begin
              // Transaction complete
              PSELx <= 1'b0;
              PENABLE <= 1'b0;
              o_done <= 1'b1;
              o_rdata <= PRDATA; // Capture read data
              o_slverr <= PSLVERR;
              state <= IDLE;
            end
            // Else, wait for PREADY (wait state)
          end

          default: ;
        endcase
      end
    end
endmodule

projects/apb/master/apb_master_tb.v
`default_nettype none

module apb_master_tb;
  // Clock and reset
  reg i_clk;
  reg i_reset_n;

  // APB master signals
  wire [31:0] PADDR;
  wire PWRITE;
  wire [31:0] PWDATA;
  wire PSELx;
  wire PENABLE;
  reg [31:0] PRDATA;
  reg PREADY;
  reg PSLVERR;

  // Control signals
  reg i_start;
  reg [31:0] i_addr;
  reg [31:0] i_wdata;
  reg i_write;
  wire o_done;
  wire [31:0] o_rdata;
  wire o_slverr;

  // Instantiate the APB master
  apb_master master (
    .i_clk(i_clk),
    .i_reset_n(i_reset_n),
    .PADDR(PADDR),
    .PWRITE(PWRITE),
    .PWDATA(PWDATA),
    .PSELx(PSELx),
    .PENABLE(PENABLE),
    .PRDATA(PRDATA),
    .PREADY(PREADY),
    .PSLVERR(PSLVERR),
    .i_start(i_start),
    .i_addr(i_addr),
    .i_wdata(i_wdata),
    .i_write(i_write),
    .o_done(o_done),
    .o_rdata(o_rdata),
    .o_slverr(o_slverr)
  );

  initial begin  
    $dumpfile("apb_master.vcd");
    $dumpvars(0,apb_master_tb);
  end 

  // Clock generation
  initial begin
    i_clk = 0;
    forever #5 i_clk = ~i_clk; // 10ns clock period
  end

  // Reset generation
  initial begin
    i_reset_n = 0;
    #20 i_reset_n = 1; // Assert reset for 20ns, then deassert
  end

  // Test sequence
  initial begin
    // Initialize signals
    i_start = 0;
    i_addr = 32'h0;
    i_wdata = 32'h0;
    i_write = 0;
    PRDATA = 32'h0;
    PREADY = 0;
    PSLVERR = 0;

    // Wait for reset to complete
    #30;

    // Test 1: Write transaction
    i_start = 1;
    i_addr = 32'h1000;
    i_wdata = 32'hDEADBEEF;
    i_write = 1;
    #10;
    i_start = 0;

    // Simulate slave response with wait cycles
    #20;
    PREADY = 1;
    #10;
    PREADY = 0;

    // Check if the i_write transaction completed successfully
    if (!o_done) begin
      $display("ERROR: Write transaction did not complete");
      $finish(1); // Exit with non-zero status
    end

    // Test 2: Read transaction
    i_start = 1;
    i_addr = 32'h1000;
    i_write = 0;
    #10;
    i_start = 0;

    // Simulate slave response with wait cycles
    #20;
    PRDATA = 32'hDEADBEEF;
    PREADY = 1;
    #10;
    PREADY = 0;

    // Check if the read transaction completed successfully
    if (!o_done) begin
      $display("ERROR: Read transaction did not complete");
      $finish(1); // Exit with non-zero status
    end

    // Check if the read data matches the expected value
    if (o_rdata !== 32'hDEADBEEF) begin
      $display("ERROR: Read data mismatch (expected DEADBEEF, got %h)", o_rdata);
      $finish(1); // Exit with non-zero status
    end

    // Test 3: Back-to-back transactions
    i_start = 1;
    i_addr = 32'h2000;
    i_wdata = 32'hCAFEBABE;
    i_write = 1;
    #10;
    i_start = 0;

    // Simulate slave response with wait cycles
    #20;
    PREADY = 1;
    #10;
    PREADY = 0;

    // Check if the i_write transaction completed successfully
    if (!o_done) begin
      $display("ERROR: Back-to-back i_write transaction did not complete");
      $finish(1); // Exit with non-zero status
    end

    i_start = 1;
    i_addr = 32'h2000;
    i_write = 0;
    #10;
    i_start = 0;

    // Simulate slave response with wait cycles
    #20;
    PRDATA = 32'hCAFEBABE;
    PREADY = 1;
    #10;
    PREADY = 0;

    // Check if the read transaction completed successfully
    if (!o_done) begin
      $display("ERROR: Back-to-back read transaction did not complete");
      $finish(1); // Exit with non-zero status
    end

    // Check if the read data matches the expected value
    if (o_rdata !== 32'hCAFEBABE) begin
      $display("ERROR: Back-to-back read data mismatch (expected CAFEBABE, got %h)", o_rdata);
      $finish(1); // Exit with non-zero status
    end

    // Test 4: Error condition
    i_start = 1;
    i_addr = 32'h3000;
    i_wdata = 32'hBADF00D;
    i_write = 1;
    #10;
    i_start = 0;

    // Simulate slave error response
    #20;
    PSLVERR = 1;
    PREADY = 1;
    #10;
    PSLVERR = 0;
    PREADY = 0;

    // Check if the error condition was handled correctly
    if (!o_done) begin
      $display("ERROR: Error condition not handled correctly");
      $finish(1); // Exit with non-zero status
    end

    // End simulation
    $display("PASS: Testbench passed");
    $finish(0); // Exit with zero status
  end
endmodule

projects/apb/master/apb_master.vcd
$date
	Fri Feb  7 16:23:12 2025
$end
$version
	Icarus Verilog
$end
$timescale
	1s
$end
$scope module apb_master_tb $end
$var wire 1 ! o_slverr $end
$var wire 32 " o_rdata [31:0] $end
$var wire 1 # o_done $end
$var wire 1 $ PWRITE $end
$var wire 32 % PWDATA [31:0] $end
$var wire 1 & PSELx $end
$var wire 1 ' PENABLE $end
$var wire 32 ( PADDR [31:0] $end
$var reg 32 ) PRDATA [31:0] $end
$var reg 1 * PREADY $end
$var reg 1 + PSLVERR $end
$var reg 32 , i_addr [31:0] $end
$var reg 1 - i_clk $end
$var reg 1 . i_reset_n $end
$var reg 1 / i_start $end
$var reg 32 0 i_wdata [31:0] $end
$var reg 1 1 i_write $end
$scope module master $end
$var wire 32 2 PRDATA [31:0] $end
$var wire 1 * PREADY $end
$var wire 1 + PSLVERR $end
$var wire 32 3 i_addr [31:0] $end
$var wire 1 - i_clk $end
$var wire 1 . i_reset_n $end
$var wire 1 / i_start $end
$var wire 32 4 i_wdata [31:0] $end
$var wire 1 1 i_write $end
$var parameter 32 5 ACCESS $end
$var parameter 32 6 IDLE $end
$var parameter 32 7 SETUP $end
$var reg 32 8 PADDR [31:0] $end
$var reg 1 ' PENABLE $end
$var reg 1 & PSELx $end
$var reg 32 9 PWDATA [31:0] $end
$var reg 1 $ PWRITE $end
$var reg 1 # o_done $end
$var reg 32 : o_rdata [31:0] $end
$var reg 1 ! o_slverr $end
$var reg 2 ; state [1:0] $end
$upscope $end
$upscope $end
$enddefinitions $end
$comment Show the parameter values. $end
$dumpall
b1 7
b0 6
b10 5
$end
#0
$dumpvars
b0 ;
b0 :
b0 9
b0 8
b0 4
b0 3
b0 2
01
b0 0
0/
0.
0-
b0 ,
0+
0*
b0 )
b0 (
0'
0&
b0 %
0$
0#
b0 "
0!
$end
#5
1-
#10
0-
#15
1-
#20
0-
1.
#25
1-
#30
0-
11
b11011110101011011011111011101111 0
b11011110101011011011111011101111 4
b1000000000000 ,
b1000000000000 3
1/
#35
b1 ;
1&
b11011110101011011011111011101111 %
b11011110101011011011111011101111 9
1$
b1000000000000 (
b1000000000000 8
1-
#40
0-
0/
#45
b10 ;
1'
1-
#50
0-
#55
1-
#60
0-
1*
#65
b0 ;
1#
0'
0&
1-
#70
0-
01
1/
0*
#75
b1 ;
1&
0$
1-
#80
0-
0/
#85
b10 ;
1'
1-
#90
0-
#95
1-
#100
0-
1*
b11011110101011011011111011101111 )
b11011110101011011011111011101111 2
#105
b0 ;
b11011110101011011011111011101111 "
b11011110101011011011111011101111 :
0'
0&
1-
#110
0-
11
b11001010111111101011101010111110 0
b11001010111111101011101010111110 4
b10000000000000 ,
b10000000000000 3
1/
0*
#115
b1 ;
1&
b11001010111111101011101010111110 %
b11001010111111101011101010111110 9
1$
b10000000000000 (
b10000000000000 8
1-
#120
0-
0/
#125
b10 ;
1'
1-
#130
0-
#135
1-
#140
0-
1*
#145
b0 ;
0'
0&
1-
#150
0-
01
1/
0*
#155
b1 ;
1&
0$
1-
#160
0-
0/
#165
b10 ;
1'
1-
#170
0-
#175
1-
#180
0-
1*
b11001010111111101011101010111110 )
b11001010111111101011101010111110 2
#185
b0 ;
b11001010111111101011101010111110 "
b11001010111111101011101010111110 :
0'
0&
1-
#190
0-
11
b1011101011011111000000001101 0
b1011101011011111000000001101 4
b11000000000000 ,
b11000000000000 3
1/
0*
#195
b1 ;
1&
b1011101011011111000000001101 %
b1011101011011111000000001101 9
1$
b11000000000000 (
b11000000000000 8
1-
#200
0-
0/
#205
b10 ;
1'
1-
#210
0-
#215
1-
#220
0-
1*
1+
#225
b0 ;
1!
0'
0&
1-
#230
0-
0*
0+
